mysampleexample/__init__.py
mysampleexample-1.0.0.data/data/my_data/data_file
mysampleexample-1.0.0.dist-info/DESCRIPTION.rst
mysampleexample-1.0.0.dist-info/METADATA
mysampleexample-1.0.0.dist-info/RECORD
mysampleexample-1.0.0.dist-info/WHEEL
mysampleexample-1.0.0.dist-info/entry_points.txt
mysampleexample-1.0.0.dist-info/metadata.json
mysampleexample-1.0.0.dist-info/top_level.txt
